amazon_scrape_toolkit/__init__.py
amazon_scrape_toolkit/main.py
amazon_scraper_toolkit-2.0.0.dist-info/LICENSE
amazon_scraper_toolkit-2.0.0.dist-info/METADATA
amazon_scraper_toolkit-2.0.0.dist-info/WHEEL
amazon_scraper_toolkit-2.0.0.dist-info/top_level.txt
amazon_scraper_toolkit-2.0.0.dist-info/RECORD
