Metadata-Version: 2.1
Name: amazon-scraper-toolkit
Version: 2.0.0
Summary: Some Helpful Classes and Functions for Scraping Amazon Data
Author: Tejas
License: The MIT License (MIT)
Project-URL: Homepage, https://github.com/KidCoderT/amazon-scraper
Keywords: amazon,scraper,toolkit
Classifier: Natural Language :: English
Classifier: Intended Audience :: Developers
Classifier: Operating System :: MacOS :: MacOS X
Classifier: Operating System :: Microsoft :: Windows
Classifier: Operating System :: POSIX
Classifier: Programming Language :: Python
Classifier: License :: OSI Approved :: BSD License
Classifier: Topic :: Software Development :: Libraries
Classifier: Topic :: Software Development :: Libraries :: Python Modules
Classifier: Topic :: Internet
Requires-Python: >=3.9
License-File: LICENSE
Requires-Dist: beautifulsoup4
Requires-Dist: requests
Requires-Dist: lxml
Provides-Extra: dev
Requires-Dist: black ; extra == 'dev'
Requires-Dist: pylint ; extra == 'dev'
Requires-Dist: pep8 ; extra == 'dev'
